erlc/__init__.py
erlc/headers.py
erlc/requests.py
erlc_rbx-0.1.0.dist-info/LICENSE
erlc_rbx-0.1.0.dist-info/METADATA
erlc_rbx-0.1.0.dist-info/WHEEL
erlc_rbx-0.1.0.dist-info/top_level.txt
erlc_rbx-0.1.0.dist-info/RECORD
