Metadata-Version: 2.1
Name: erlc-rbx
Version: 0.1.0
Summary: a better (and open-source) wrapper for the ERLC api.
Home-page: https://github.com/thatgurkangurk/gurkz.me
Author: Gurkan
Author-email: hello@gurkz.me
License: GPL 3.0
Project-URL: Source, https://github.com/thatgurkangurk/erlc.py
Project-URL: Bug Tracker, https://github.com/thatgurkangurk/erlc.py/issues
Classifier: Development Status :: 3 - Alpha
Classifier: Intended Audience :: Developers
Classifier: License :: OSI Approved :: GNU General Public License v3 (GPLv3)
Classifier: Natural Language :: English
Classifier: Programming Language :: Python :: 3.11
Classifier: Programming Language :: Python :: 3.12
Classifier: Programming Language :: Python :: 3.13
Classifier: Topic :: Utilities
Requires-Python: >=3.10,<3.14
License-File: LICENSE
Requires-Dist: requests >=2.32
